CHANGELOG.md
MANIFEST.in
README.rst
requirements-py2.txt
requirements.txt
setup.cfg
setup.py
tapispy/__init__.py
tapispy/actors.py
tapispy/async.py
tapispy/resource_exceptions.json
tapispy/resources.json
tapispy/response_handlers.py
tapispy/tapis.py
tapispy.egg-info/PKG-INFO
tapispy.egg-info/SOURCES.txt
tapispy.egg-info/dependency_links.txt
tapispy.egg-info/not-zip-safe
tapispy.egg-info/requires.txt
tapispy.egg-info/top_level.txt
tapispy/clients/__init__.py
tapispy/clients/create.py
tapispy/clients/delete.py
tapispy/clients/exceptions.py
tapispy/clients/list.py
tapispy/clients/subscribe.py
tapispy/clients/subscribtions.py
tapispy/files/__init__.py
tapispy/files/copy.py
tapispy/files/delete.py
tapispy/files/download.py
tapispy/files/exceptions.py
tapispy/files/history.py
tapispy/files/import_files.py
tapispy/files/list.py
tapispy/files/mkdir.py
tapispy/files/move.py
tapispy/files/pems_delete.py
tapispy/files/pems_list.py
tapispy/files/pems_update.py
tapispy/files/upload.py
tapispy/resources/api_actors.json.j2
tapispy/resources/api_admin.json.j2
tapispy/resources/api_apps.json.j2
tapispy/resources/api_clients.json.j2
tapispy/resources/api_files.json.j2
tapispy/resources/api_jobs.json.j2
tapispy/resources/api_meta.json.j2
tapispy/resources/api_monitors.json.j2
tapispy/resources/api_notifications.json.j2
tapispy/resources/api_postits.json.j2
tapispy/resources/api_profiles.json.j2
tapispy/resources/api_systems.json.j2
tapispy/resources/api_transforms.json.j2
tapispy/resources/deprecated_resources.json.j2
tapispy/resources/misc.json.j2
tapispy/swaggerpy/__init__.py
tapispy/swaggerpy/client.py
tapispy/swaggerpy/codegen.py
tapispy/swaggerpy/http_client.py
tapispy/swaggerpy/processors.py
tapispy/swaggerpy/swagger_model.py
tapispy/tenants/__init__.py
tapispy/tenants/tenants.py
tapispy/tokens/__init__.py
tapispy/tokens/create_access_token.py
tapispy/tokens/exceptions.py
tapispy/tokens/refresh_tokens.py
tapispy/utils/__init__.py
tapispy/utils/load_configs.py
tapispy/utils/response_handlers.py
tapispy/utils/save_configs.py