Metadata-Version: 1.1
Name: tapispy
Version: 0.1.0.dev0
Summary: Python SDK for the Tapis computing platform.
Home-page: https://github.com/tapis-project/tapispy
Author: Texas Advanced Computing Center
Author-email: jstubbs@tacc.utexas.edu
License: BSD
Platform: UNKNOWN
Classifier: Development Status :: 4 - Beta
Classifier: Intended Audience :: Developers
Classifier: License :: OSI Approved :: BSD License
Classifier: Natural Language :: English
Classifier: Programming Language :: Python :: 2
Classifier: Programming Language :: Python :: 2.7
Classifier: Programming Language :: Python :: 3
Classifier: Programming Language :: Python :: 3.3
Classifier: Programming Language :: Python :: 3.6
